pyvxlapi/__init__.py
pyvxlapi/py.typed
pyvxlapi-0.1.2.dist-info/WHEEL
pyvxlapi-0.1.2.dist-info/METADATA
pyvxlapi-0.1.2.dist-info/RECORD
