Metadata-Version: 2.3
Name: pyvxlapi
Version: 0.1.2
Summary: Python Wrapper for Vector XL Driver Library
Requires-Python: >=3.9
Project-URL: homepage, https://github.com/mikisama/pyvxlapi
